LICENSE
MANIFEST.in
README.md
setup.cfg
setup.py
tap_xero/__init__.py
tap_xero/client.py
tap_xero/context.py
tap_xero/streams.py
tap_xero/transform.py
tap_xero/schemas/accounts.json
tap_xero/schemas/addresses.json
tap_xero/schemas/allocations.json
tap_xero/schemas/attachments.json
tap_xero/schemas/bank_transactions.json
tap_xero/schemas/bank_transfers.json
tap_xero/schemas/branding_themes.json
tap_xero/schemas/contact_groups.json
tap_xero/schemas/contacts.json
tap_xero/schemas/credit_notes.json
tap_xero/schemas/currencies.json
tap_xero/schemas/employees.json
tap_xero/schemas/expense_claims.json
tap_xero/schemas/invoices.json
tap_xero/schemas/items.json
tap_xero/schemas/journals.json
tap_xero/schemas/line_items.json
tap_xero/schemas/linked_transactions.json
tap_xero/schemas/manual_journals.json
tap_xero/schemas/nested_invoice.json
tap_xero/schemas/organisations.json
tap_xero/schemas/overpayments.json
tap_xero/schemas/payment_terms.json
tap_xero/schemas/payments.json
tap_xero/schemas/phones.json
tap_xero/schemas/prepayments.json
tap_xero/schemas/purchase_orders.json
tap_xero/schemas/quotes.json
tap_xero/schemas/receipts.json
tap_xero/schemas/repeating_invoices.json
tap_xero/schemas/reports-balance_sheet.json
tap_xero/schemas/reports-profit_and_loss.json
tap_xero/schemas/tax_rates.json
tap_xero/schemas/tracking_categories.json
tap_xero/schemas/users.json
tap_xero/schemas/validation_errors.json
tap_xero_reports.egg-info/PKG-INFO
tap_xero_reports.egg-info/SOURCES.txt
tap_xero_reports.egg-info/dependency_links.txt
tap_xero_reports.egg-info/entry_points.txt
tap_xero_reports.egg-info/requires.txt
tap_xero_reports.egg-info/top_level.txt